.project
.pydevproject
MANIFEST.in
README
README.serial
ez_setup.py
gendoc.sh
setup.py
bin/pyvc-console.py
bin/pyvc-createimage.py
bin/pyvc-start.py
bin/pyvc-status.py
bin/pyvc-stop.py
bin/pyvc-trace.py
bin/pyvcd.py
demos/stupid.xml
demos/multi/four.xml
demos/multi/hostrealmachine.xml
demos/multi/mixedmulticast.xml
demos/multi/multicast.xml
demos/multi/multihomed.xml
demos/multi/multiip.xml
demos/multi/netrealmachine.xml
demos/multi/two.xml
demos/multi/xen.xml
demos/network/two.xml
demos/python/fakenet.py
demos/python/multi.py
demos/python/multi_hj.py
demos/python/multi_hj_pyvc.py
demos/python/multicast.py
demos/python/single.py
demos/python/vcml.py
demos/single/qemu.xml
demos/single/qemu_router_dhcp.xml
demos/single/qemu_tap.xml
demos/single/qemu_user.xml
demos/single/uml.xml
demos/single/uml_router_dhcp.xml
demos/single/uml_tap.xml
demos/term/term_client.py
demos/term/term_server.py
demos/term/term_singlesystem.py
eggs/setuptools-0.6c5-py2.4.egg
etc/pyVC.ini
lib/pyVC/Machine.py
lib/pyVC/RemoteMachine.py
lib/pyVC/Term.py
lib/pyVC/__init__.py
lib/pyVC/errors.py
lib/pyVC/pyVCd.py
lib/pyVC/vcml.xsd
lib/pyVC.egg-info/PKG-INFO
lib/pyVC.egg-info/SOURCES.txt
lib/pyVC.egg-info/dependency_links.txt
lib/pyVC.egg-info/not-zip-safe
lib/pyVC.egg-info/requires.txt
lib/pyVC.egg-info/top_level.txt
lib/pyVC/Disks/Base.py
lib/pyVC/Disks/Floppy.py
lib/pyVC/Disks/ISO.py
lib/pyVC/Disks/Image.py
lib/pyVC/Disks/Physical.py
lib/pyVC/Disks/__init__.py
lib/pyVC/Helpers/Base.py
lib/pyVC/Helpers/DHCP.py
lib/pyVC/Helpers/Interface.py
lib/pyVC/Helpers/Router.py
lib/pyVC/Helpers/Tools.py
lib/pyVC/Helpers/__init__.py
lib/pyVC/Networks/Base.py
lib/pyVC/Networks/Bridge.py
lib/pyVC/Networks/Multicast.py
lib/pyVC/Networks/TAP.py
lib/pyVC/Networks/Tools.py
lib/pyVC/Networks/User.py
lib/pyVC/Networks/VDE1.py
lib/pyVC/Networks/__init__.py
lib/pyVC/Specifications/Base.py
lib/pyVC/Specifications/VCML.py
lib/pyVC/Specifications/__init__.py
lib/pyVC/VirtualMachines/Base.py
lib/pyVC/VirtualMachines/QEMU.py
lib/pyVC/VirtualMachines/UML.py
lib/pyVC/VirtualMachines/Xen.py
lib/pyVC/VirtualMachines/__init__.py
tools/config.py
tools/pyvc-connect.py
tools/validate.py
vbuild/.cvsignore
vbuild/Makefile
