Metadata-Version: 1.0
Name: pyVC
Version: 1.3.0
Summary: A set of Python tools for virtual cluster computing
Home-page: http://www.cs.mtsu.edu/pyvc
Author: Zach Lowry
Author-email: zach@cs.mtsu.edu
License: BSD
Download-URL: http://cheeseshop.python.org/pypi/pyVC
Keywords: virtualization qemu uml vde xen vcml xml pyro cluster hpc
Platform: POSIX
Classifier: Development Status :: 4 - Beta
Classifier: Environment :: Console
Classifier: Intended Audience :: Science/Research
Classifier: Intended Audience :: System Administrators
Classifier: License :: OSI Approved :: BSD License
Classifier: Natural Language :: English
Classifier: Operating System :: POSIX
Classifier: Operating System :: POSIX :: Linux
Classifier: Programming Language :: Python
Classifier: Topic :: Software Development :: Libraries :: Python Modules
Classifier: Topic :: System :: Clustering
Classifier: Topic :: System :: Distributed Computing
Classifier: Topic :: System :: Emulators
